LICENSE.txt
MANIFEST.in
README.md
setup.py
snor/__init__.py
snor/conf.py
snor/models.py
snor/server.py
snor/utils.py
snor.egg-info/PKG-INFO
snor.egg-info/SOURCES.txt
snor.egg-info/dependency_links.txt
snor.egg-info/entry_points.txt
snor.egg-info/requires.txt
snor.egg-info/top_level.txt
snor/clients/__init__.py
snor/clients/transmission.py
snor/clients/utorrent.py
snor/search/__init__.py
snor/search/torrentzeu.py
snor/static/css/bootstrap-responsive.css
snor/static/css/bootstrap-responsive.min.css
snor/static/css/bootstrap.css
snor/static/css/bootstrap.min.css
snor/static/img/glyphicons-halflings-white.png
snor/static/img/glyphicons-halflings.png
snor/static/img/imdb-icon16.png
snor/static/img/imdb-icon24.png
snor/static/img/imdb-icon32.png
snor/static/img/imdb.png
snor/static/js/bootstrap.js
snor/static/js/bootstrap.min.js
snor/static/js/handlebars.min.js
snor/static/js/jquery.min.js
snor/static/js/site.js
snor/templates/base.html
snor/templates/home.html
snor/templates/login.html
snor/templates/modal_browse.html
snor/templates/search.html
snor/templates/search_result.html
snor/templates/settings.html
snor/templates/show.html
snor/templates/show_add.html
snor/templates/show_add_choice.html