Metadata-Version: 1.0
Name: snor
Version: 0.0.8
Summary: A very lightweight "sickbeard for torrents" 
Home-page: https://github.com/tax/snor
Author: Paul Tax
Author-email: paultax@gmail.com
License: MIT licence, see LICENCE.txt
Platform: UNKNOWN
